CHANGES.txt
LICENSE.txt
MANIFEST.in
README.txt
requirements.txt
setup.py
auth_userpass.egg-info/PKG-INFO
auth_userpass.egg-info/SOURCES.txt
auth_userpass.egg-info/dependency_links.txt
auth_userpass.egg-info/requires.txt
auth_userpass.egg-info/top_level.txt
test/test_userpass.py
userpass/__init__.py
userpass/userpass.py