Metadata-Version: 1.0
Name: auth-userpass
Version: 0.5.0
Summary: Simple but not so secure username and password storage and retrieval
Home-page: https://github.com/francisluong/py-auth-userpass
Author: Francis Luong (Franco)
Author-email: networkascode@definefunk.com
License: LICENSE.txt
Platform: UNKNOWN
